{"Banda":[{"cityName":"Atarra","cityCode":"126","Atarra":["Adharori","Ajit Para","Akabarpur","Amiliha","Amwan","Anathuwa","Anchwara","Atarra (Rural)","Au","Badousa","Bagha","Baghela Wari","Bahoran Purwa","Ballan","Bambura","Banai","Barachha","Barchha Dodiya","Barehenda","Barsanda Buzurg","Barsanda Khurd","Basrehi","Beri Birhand","Bhadawal","Bhagwatpur","Bhatoura","Bhawanipur","Bhusasi","Bigahna","Bil Gaon","Birampur","Bisanda (Rural)","Budhauli","Chak Bhatoura","Chak Takuli","Chandour","Chandrayal","Chaunsarh","Chhantupur Kalan","Chhibaon","Dabhani","Dadhwa Manpur","Dhaurahi Mafi","Dixit Wara","Dongari","Dubariya","Durai Mafi","Gadaon","Gajpatipur Kalan","Gajpatipur Khurd","Ghoori","Ghuraunda","Gobariya Buzurg","Gonda","Gumai","Hadaha Mafi","Hastam","Hunda","Itara Khurd","Itara Malauli","Jabarapur","Jakhni","Jamrehi","Kandohara","Karari","Kergehana","Khamhaura","Khataura","Kheriya","Khurhand","Kila Madfa","Kolouha","Koorahu","Kullu Khera","Kusama","Lamehta","Look","Ludhoura","Lyonjha","Madhwara","Mahotara","Mahuta","Mahuwa","Makari","Mau","Nagnedhi","Nagwara","Nai","Nandan Mau","Nandna","Oraha","Oran (Rural)","Pahari Khurd","Palpur","Para","Partappur","Pataunda","Pawai","Pindkhar","Pouhar","Punahur","Quazipur","Rahusat","Rasin","Rauli Kalayanpur","Sahewa","Sangrampur","Semaria Mirdaha","Semariya Jadid","Semariya Kushal","Shahpur Sani","Siklodhi","Singhpur Mafi","Sudinpur","Syohad","Takuli","Tarsuma","Tenduhi","Tendura","Tera(B)","Thanair","Titihara","Turra","Udaipur","Umrehanda","Utarwan"]},{"cityName":"Baberu","cityCode":"182","Baberu":["Achhah","Achhareel","Adhawan","Ahar","Alampur","Aliha","Amar Ganj","Amethee","Amlohra","Amlokhar","Andaura","Andoulee","Anousa","Anvan","Aoudaha","Armar","Arthara","Arvaree","Augasi","Baberu Dehat","Bacal","Bachhaundha","Bachhaundha Sanee","Bada Gaon","Badaulee","Bagehta","Baghanda","Baghela","Bamharola","Bamroula Sanee","Ban Baroulee","Bankat","Bantharee","Baraolee","Baroulee Azam","Beera","Beldan","Bena Mau","Bhabhuwa","Bhadenadu","Bhadvari","Bhandav","Bhantee","Bhatoulee","Bhitee","Bil Gavan","Birravan","Bisandee","Budhoulee","Byonja","Chakrehee","Charaka","Chhilolar","Daftara","Dando","Dataura","Deh","Deorar","Devratha","Dhundhui","Dighaura","Ekauna","Enguva","Etara Badhounee","Etavan","Funfudee","Gaura","Ghan Saul","Ghosad","Goura Lakhanpur","Gujenee","Guroulee Saphaee","Guroulee Sukla","Hardoulee","Jalalpur","Jamoo","Janvara","Jarohra","Joraurpur","Jugrehlee","Kabeerpur","Kadohar","Kairee","Kalana","Kamasin","Karahulee Maphi","Karinga","Kathar","Kauhara","Kayal","Kelahanuva","Khamarkha","Kharaulee","Khatan","Kheda","Kitahai","Kolaura","Konee","Koraree","Kori Khurd","Korra Bujurg","Korrahee","Korram","Kuchendo","Kuchouli","Kumedha","Kumheda Sanee","Lakhanpur","Lakheepur","Laulee Teera Mau","Lodhaura Khurd","Lohara","Maduva","Majheevan","Majhila","Majhiva Sani","Mamsee Khurd","Mankahndee","Mantha","Maraulee","Marka","Matehana","Mau","Mavae Junnardar","Mavae Khurd","Mavai","Milathu","Miya Baroulee","Mudvara","Murwal","Museevan","Narayanpur","Nelathu","Nibhaura","Pachhahan","Pakhroulee","Palee","Palhari Sani","Palhree","Pandaree","Pannaha","Para Bannu Begam","Para Bihari","Paras","Parsaulee","Patvan","Pavaiya","Pindaran","Pista","Poon","Rachha","Raghoupur","Ragoulee","Rampurwa","Ranipur","Rasulpur","Rayan","Samgara","Samsuddeenpur","Sanda","Sanda Sanee","Santar","Sathi","Satnyava","Saya","Sayohat","Shahpur","Shiv","Sikaree Lakhanpur","Simounee","Sonahula","Sonahulee","Tarayan","Tera Dar Senda","Tharthuwa","Tilousa","Tola Kajee","Tola Kalan","Udakee Mafee","Umarahanee","Umaree","Vinwat"]},{"cityName":"Banda","cityCode":"199","Banda":["Achharaund","Adari","Alona","Amara","Amaraiya","Amchauli","Amli Kaur","Amlor","Arbai","Arsaunda","Atarahat","Bachheura","Badeha","Badehara","Bahadurpur","Bahinga","Bahundari","Bakachha","Bambiya","Bandha Purwa","Baragaon","Barehta","Barethi Askaran","Barethi Kalan","Bargahani","Barokhar Khurd","Basahari","Basdhari","Benda","Bhadauli","Bharkhari","Bhatha","Bhawani Purwa","Bhawanipur","Bhindaura","Bhujauli","Bhujrakh","Bhurendi","Bichhawahi","Bilbai","Bisanda Khurd","Budheda","Byonja","Chahitara","Chakchatgan","Chamraha","Chandwara","Chatkan","Chhanehara Lalpur","Chhapar","Chheharao","Chhirahuta","Chilehata","Chilla","Chilli","Dadariya","Dandamau","Datarauli","Dhaunsar","Dighwat","Dingwahi","Doha","Dohatara","Durendi","Etawan","Fatpurwa","Gadariya","Gadola","Gajani","Galauli","Ganchha","Garauti","Gaura","Gauri Kalan","Gauri Khurd","Gazipur","Godhani","Goharwa","Goyara Mugali","Gugauli","Gureh","Hardauli","Hateti Purwa","Hathaura","Ichhawar","Jakhaura","Jamalpur","Jamunipur","Jamuwa","Jari","Jariya","Jasaipur","Jaspura","Jauharpur","Jaurahi","Jhanjhari","Kalyanpur","Kamnaudi","Kana Khera","Kanwara","Karachha","Karahiya","Karbai","Kathsemar","Katrawal","Khairada","Khairei","Khajuri","Khaptiha Kalan","Khaptiha Khurd","Khaunda","Khokharahi","Kukuwa Khas","Kul Kumhari","Kunwarpur","Kurauli","Kurseja","Ladaka Purwa","Lalauli","Lama","Lasada","Laumar","Lohara","Lohari","Luktara","Macha","Madauli Kalan","Madauli Khurd","Mahabara","Mahedu","Mahokhar","Mahui","Maraka","Marauli","Marjha","Mata","Mataundh(Gramin)","Mathana Khera","Maudaha","Mawai Buzurg","Mawai Ghat","Mawai Lidad","Mirgahani","Mohan Purwa","Mungus","Nada Deo","Narauli","Narayarh","Nari","Narjita","Nimnipar","Niwaich","Pachanehi","Pachkauri","Pachulla","Padarathpur","Paderi","Padohara","Pailani","Palara","Palhari","Pandui","Paparenda","Parsaunda","Pathari","Piparahari","Pipargawan","Piparodar","Pipri(Mataundh)","Rampur","Rehutan","Reona","Sabada","Sadi Madanpur","Sahinga","Sahoorpur","Saimara","Saimari","Sandi","Shekhupur","Sikahula","Sikuwa","Sindhan Kalan","Sindhan Khurd","Sindhauli","Singhpur","Sohana","Sonamau","Sonrahi","Surauli","Tangamau","Tara","Teiveni","Terahi Mafi","Tindawari Rural","Tindwara","Toliya","Ujrehta","Wasilpur"]},{"cityName":"Naraini","cityCode":"175","Naraini":["Aila","Ajitpur","Akbarpur Girwan","Amritpur Kherwa","Arjunah","Bachhei","Badausa Sani","Badeh Kalinjar","Badeha Seodha","Bagaha","Bahadurpur Kalinzar","Baheri","Bal Khera","Bande","Bansaka","Bansi","Baraichha","Barimanpur","Bariyari","Barkola Kalan","Barokhar Buzurg","Barokhar Khurd","Barsanda Manpur","Barua Kalinjar","Baruwa Syodha","Baryarpur","Bhadaiyan","Bhasround","Bhawai","Bilharka","Birauna","Bulakipur","Chakk Mafi","Chandpura","Chatsara","Chhataini","Dahuri","Dalhawa","Deorar","Divali","Dubari","Durgapur","Gadha","Gadha Khurd","Gadhi Chandpur","Gahabara","Gaidi Mafi","Gaur Shivpur","Girdharpur","Girwan","Gokhia","Gopara","Gore Mau Kalan","Goremau Khurd","Govindpur","Gudha Kalan","Hadaha","Haripur","Husenpur Kalan","Husenpur Khurd","Jahangirabad","Jamapur","Jamawara","Jarar","Kabauli","Kahala","Kalhara","Kalyanpur","Kanaya","Karatal","Katara Kalinjar","Kazipur Girwan","Kesaruwa","Khadiha","Khalari","Khandeura","Khanpur","Kharaunch","Kherwa","Khohi","Khujamariya","Kila Kalinzar","Kiratpur","Kolawal Raipur","Kulsari","Lad Pahari","Lahura","Lahureta","Lama Khutila","Madhopur","Mahui","Mahurchha","Majhgawan Seodha","Malehra Niwada","Manipur","Manpur Khurd","Masani","Masauni Bharatpur","Masuri","Mau Girwan","Mirzapur","Moongus","Motiyari","Mudi","Mukera","Mungaura","Muradpur","Murwan","Nahari","Nandwara","Naraini (Dehat)","Nasaratpur","Naseni","Naugawan","Nauhai","Nedhuwa","Nibhaura","Nibi","Nihalpur","Pachokhar","Pagnara","Pahari Mafi","Paharpur","Pahi","Paigamberpur","Palhari","Palhari Badausa","Panchampur (B)","Panchampur(Girwan)","Paramai","Parasahar","Parsidhapur","Pataura","Pathara","Patraha","Paundara","Pipara","Piparhari","Pithaurabad","Piyar","Pongari","Prempur","Pukari","Purainiya","Ragauli Bhatpura","Rajapur","Ram Nagar Nisf","Rampur","Rampur Murdi","Ran Khera","Ranipur","Ranjitpur","Raxi","Rehunchi","Riga","Risaura","Sadha","Sakatpur","Santpur","Sarai Zadid","Saripur","Sarswaha","Saunta Kalinzar","Sauta Syodha","Sedhaura","Sejahari","Shah Patan","Shahbajpur","Shahpur","Sidhalla","Singhauti","Syodha","Tarahati Kalinzar","Tarkhari","Tera Girwan"]}]}