{"Jalandhar":[{"cityName":"Jalandhar I","cityCode":"140","Jalandhar I":["Aladinpur","Alipur","Arjanwal","Bahudinpur","Bambianwali","Barsal","Beas Pind","Bhagwanpur","Bhojowal","Bolina","Budhiana","Chachowal","Chak Daulatpur","Chak Jethpur","Chananpur","Chander Sain","Chandpur","Chetewan","Chhatowali","Chomon","Chuhan","Chuharwali","Chukhiara","Damudarpur","Daroli Kalan & Daroli Khurd","Daulatpur","Daulatpur","Dhada","Dhanal","Dhandaur","Dhandauri","Dhepur","Dhin","Dianatpur","Diwali","Dolike Sunderpur","Duhra","Dumunda","Fatehpur","Fatehpur","Ghurial","Goalpind","Gopalpur","Halotali","Hamiri Khera","Hardo Pharala","Haripur","Hazara","Isharwal","Jaganpur","Jagral","Jagrawan","Jaitewali","Jalbhe","Jalpot","Jamsher","Jandiali","Jethpur","Johal","Kabulpur","Kadianwali","Kala Bakra","Kalra","Kandola","Kangniwal","Kanuni","Kapur Pind","Karari","Kariana","Kasampur","Kathar","Khiala","Khichipur","Khun Khun","Khurdpur","Khusropur","Kishangarh","Kishanpur","Kot Kalan","Kot Khurd","Kotla","Kotli Jamiat Singh","Kotli Sheikhan","Kotli Than Singh","Kukar Pind","Kupur","Lesariwala","Lohar","Luhar Nangal","Lutera Kalan","Lutera Khurd","Mahadipur","Mander","Manko","masanian","Mazaffarpur","Miranpur","Mohammadpur","Mubarakpur","Muradpur","Mussapur","Nangal Fateh Khan","Nangal Jamalpur","Nangal Purdil","Nangal Salempur","Nangal Shama","Nauli","Naurangpur","Nawan Pind","Nizamudinpur","Padhiana","Paras Rampur","Partappur","Patara","Pholriwala","Phulpur","Puranpur","Raipur","Rehmanpur","Salarpur","Salempur Masandan","Sangowal","Saprai","Sarnana","Semi","Shahpur","Shahpur","Shekhe Pind","Sherpur","Sikanderpur","Sitalpur","Subhana","Sufipind","Talhan","Talwandi Araian","Talwara","Ucha","Udesian","Udhopur","Usmanpur"]},{"cityName":"Jalandhar II","cityCode":"242","Jalandhar II":["Abadan","Adagil","Aema","Akhara","Alamgir","Alampur","Ali Chak","Ali Khel","Ambhgarh","Athaula","Badala","Badshahpur","Bagota","Bahopur","Bajra","Ball","Bansian","Barchuhi","Bashesherpur","Basti Ibrahim Khan","Behram Shoerista","Bhagwanpur","Bhakhu Nangal","Bhathe","Bhatija Randhawa","Bhatnura Labana","Bhattian","Bhel","Bhikha Nangal","Bhundian","Bisrampur","Brahampur","Bula","Bulandpur","Bullowal","Butran","Chaharke","Chak Bashesharpur","Chak Hamza","Chak Hussainpur","Chak Mehamudpur","Chak Mochipur","Chak Ram Singhpur","Chak Rampur Lallian","Chak Shakur","Chakrala","Chamiara","Chamiari","Charar","Chhotapind Alias Barapind","Chhuhar","Chitti","Chogawan","Cholang","Chuhan","Daffarwal","Dalla","Darawan","Daryapur","Dasupur","Daudpur","Desalpur","Devi Dasspur","Dhadda","Dhaliwal","Dhamooli","Dhirowal","Dhirpur","Dhogri","Dhurial","Dialpur","Dingrian","Dittu Nangal","Dode","Dugri","Faridpur","Fateh Jalal","Fattupur","Fazalpur","Fazilpur","Firoz","Gadaipur","Gaddowali","Gakhal","Garhi Bakhsha","Gazipur","Gehlar","Ghorewahi","Ghug","Ghugg","Ghumiara","Giganwal","Gill","Gobindpur","Gokalpur","Gona Chak","Haller","Hasan Munda","Hassanpur","Hirapur","Hussainpur","Ispur","Ittan Badhi","Jaffal Jhingar","Jagan","Jalalwal","Jalla Singh","Jallowal","Jamalpur","Jande Sarai","Jandir","Jandu Singha","Kahlwan","Kala Bhian","Kala Khera","Kalianpur","Kandhala Guru","Kartarpur (Rural)","Khaira Majha","Khanke Fatehgarh","Kharal Kalan","Khojkipur","Khojpur","Khusropur","Kingra Chowala","Kohala","Kohja","Kotla","Kotla","Kotli Araian","Kotli Bagbana","Kotli Sazawar","Kotli Viran","Kuddowal","Kurala","Kurali","Kureshian","Kutlupur","Ladhra","Lalapur","Lallian Kalan","Lallian Khurd","Lambra","Lambri","Laroya","Lidhran","Lohar","Lohar","Lohian","Madar","Madhopur","Mahaddipur","Malian","Malko","Malli nangal","Mamandpur","Manak rai","Manan","Mand","Mand","Mangeki","Mansurpur","Mari Harnia","Mir Chhota","Mirpur","Moga","Mokal","Mokhe","Momanpur","Muchrowal","Muridpur","Musapur","Mustfapur","Nahal","Nahal","Najka","Nandanpur","Nangal Fida","Nangal Manohar","Naranwali","Narpur","Naugajja","Nijran","Nurpur","Nussi","Pachranga","Pandori Nijran","Parapind","Passan","Patial","Pattar Kalan","Pattar Khurd","Pawar","Rahimpur","Raipur Rasulpur","Rajab","Rajpur","Ram Singhpur","Rampur Lallian","Randhawa Masandan","Rani Bhatti","Raowali","Rastgo","Rasulpur Brahmna","Rasulpur Khurd","Rohjri","Sada Chak","Sada Chak","Sagranwali","Salala","Samipur","Sanaura","Sandham","Sangal Sohal","Sarai Khas","Sarmastpur","Sarobad","Satowali","Sehjhangi","Shaffipur","Shafipur","Shakarpur","Shivdaspur","Siawal","Sikandarpur","Singh","Singhpur","Sohalpur","Sondha Chak","Sudana","Sura","Tajpur","Talwandi Abdar","Talwandi Bhilan","Talwandi Jhandir","Talwara","Tandi","Trar","Wadala","Wariah","Wariana","Zinokot"]},{"cityName":"Nakodar","cityCode":"146","Nakodar":["Addi","Adraman","Akbarpur Kalan","Akbarpur Khurd","Alewali","Allowal","Angi Kiri","Aulak","Awan Chaharmi","Awan Khalsa","Baghela","Bagpur","Bajuha Kalan","Bajuha Khurd","Bal Hukmi","Bal Kohna","Baloki","Bangiwal","Bara Aslam","Bara Sidhpur","Bath","Baupur","Behar","Bhodipur","Bhullar","Bila Nawab","Bir Baloki","Bir Pind","Bir Udhowal","Bitlan","Boparai","Budhi Pind","Bulanda","Chak Kalan","Chak Khurd","Chak Muglani","Chak Pirpur","Chak Vendal","Chanian","Chhaula","Chuhar","Dhadda Dilkhapur","Dhadda Haripur","Dhadda Hundal","Dhadda Lehna","Dhaliwal","Dherian","Dhuggar","Durgawal","Fazalpur","Gandhran","Gaunsuwal","Gill","Gohir","Gura","Haer","Haripur","Hussainabad","Hussainpur","Jahangir","Jamaitgarh Alias Khosa","Jawinde","Jhungian","Kang Sahbu","Kang Sahibrai","Kangna","Khaira Mushtarka","Khairulapur","Khanpur Dhadda","Khiwa","Khurampur","Khursheidpur","Kotla Bhagu","Kotla Jangan","Kotla Sudan","Ladhewali","Ladhran","Leel","Littran","Lohar Nangal","Lohgarh","Maheru","Mahunwal","Mallian Kalan","Mallian Khurd","Malri","Malwal","Mandiala","Mehatpur","Mehmudpur","Mehsampur","Miranpur","Mirpur","Muhem","Mundh","Musewal","Muzaffarpur","Nakodar (Rural)","Nangal Jiwan","Nawan Pind Araian","Nawan Pind Dakhni","Nurpur","Pandori Khas","Pandori Sheikhan","Panjgrain","Pasarian","Pindori Rajputan","Qaimwala","Rahimpur","Raibwal","Raipur Araian","Raipur Gujran","Ramunwal","Rangra","Rasulpur","Rasulpur","Rasulpur Kalan","Rauli","Saham","Sahariwal","Saidupur","Samailpur","Sangowal","Sarai Kham","Sarih","Sehowal","Shah Salempur","Shahpur","Shahpur","Shankar","Sharakpur","Sianiwal","Sidhwan","Singhpur","Singhpur","Sohal Khurd","Tahli","Talwandi Bharo","Talwandi Salem","Tandaura","Thabalke","Tut","Udhowal","Uggi","Ummarwal Billa","Umrewal"]},{"cityName":"Phillaur","cityCode":"229","Phillaur":["Achan Chak","Adekali","Ajtani","Akalpur","Anihar","Apra","Ashaur","Atta","Atti","Aujla","Aujla","Bachhowal","Bainapur","Bajar","Bakapur","Bansian","Bansian","Bara Pind","Bath","Batura","Begampur","Bhadarpur","Bhaini","Bhallowal","Bhandal Buta","Bhandal Himmat","Bhandal Sahib Rai","Bhangala","Bhar Singhpur","Bhardwaji","Bharuwal","Bhattian","Bhoda","Bhullar","Bhundri","Bilga","Bir Bansian","Bir Ganna Pind","Bir Jaitowal","Bir Phillaur","Birk","Bundala","Buraj Hassan","Burj Kaila","Burj Pukhta","Chachrari","Chak Desraj","Chak Dhotran","Chak Sahbu","Cheema Kalan","Cheema Kalan","Cheema Khurd","Cheema Khurd","Chhaula","Chhokran","Cholang","Chuheki","Daduwal","Dalewal","Dalla","Danduwal","Darapur","Dhanda","Dhandwar","Dhanipind","Dhesian Kahna","Dhesian Sang","Dhindsa","Dhinpur","Dholeta","Dialpur","Dosanjh Kalan","Dosanjh Khurd","Fatehgarh Lakha","Fatehgarh Nihal","Fatehpur","Gadra","Gag Alias Dhagara","Ganna Pind","Garha","Garhi Mahansingh","Ghurka","Giddarpindi","Gohawar","Gulamgarh","Gumtala","Gumtali","Gura","Gursian Nihal","Gursian Piran","Hardo Sangha","Hardo Sheikh","Haripur","Indna Kalaske","Jago Sangha","Jaitowal","Jaja Kalan","Jaja Khurd","Jajo Mazara","Jand","Jhungian Mahansingh","Johal","Kala","Kandola Kalan","Kandola Khurd","Kang Araian","Kang Jagir","Kangniwal","Kariana","Kat Palon","Katana","Khaira","Khanpur","Khela","Khojpur","Khokhewal","Kot Badal Khan","Kot Garewal","Kotli Khakhian","Kutbewal","Ladhar Kalan","Ladhar Khurd","Ladian","Lakhanpal","Lalian","Landara","Langrian","Lasara","Lehal","Lohgarh","Machhiana","Mahal","Mainwal","Mandi","Mansurpur","Masani","Matfallu","Mathadda Khurd","Mau","Mawai","Mehsampur","Miranpur","Mithra","Moron","Muthadda Kalan","Muzara","Nagar","Nagra","Nahal","Nangal","Nanu Mazara","Nat","Nathewal","Nawan Pind Naicha","Nurewal","Pabwan","Paddi Jagir","Paddi Khalsa","Pal Qadiam","Palnau","Pandori Jagir","Pandori Musharkati","Panj Dhera","Partappura","Pasla","Pasli","Pawahri","Phalpota","Pharwala","Phillaur","Phillaur Qilla","Powadra","Qadian","Raipur Araian","Raipur Sagnewal","Rajauri","Rajgomal","Rajowal","Rajpur","Ramewal","Ramgarh","Rampur","Randhawa","Ranwan","Rara","Rasulpur","Rupowal","Rurka Kalan","Rurka Khurd","Rurki","Sadhara","Sagarpur","Saidowal","Saifabad","Salkiana","Samrai","Samrari","Sangatpur","Sangha Jagir","Sangha Khalsa","Sangowal","Sargundi","Sarhal Mundi","Sarhali","Shadipur","Shahpur","Shampur","Shamsabad","Sheikhupur","Sherpur","Sidhu Harisingh","Sidhu Mutsadi","Sultanpur","Sunar Kalan","Sunar Khurd","Sundar Tatar","Surja","Tagar","Takhan Muzara","Takhar","Talwan","Tehang","Thala","Thammanwal","Turan","Umarpur","Uppal Bhupa","Uppal Jagir","Uppal Khalsa"]},{"cityName":"Shahkot","cityCode":"177","Shahkot":["Aidalpur","Akalpur","Aliwal","Badli","Badshahpur","Bagga","Bahmanian","Bajwa Kalan","Bajwa Khurd","Balnau","Bara Budhsingh","Bara Jagir","Bara Jodhsingh","Baupur","Bhando","Bhoyapur","Billi Baraich","Billi Chaharmi","Billi Chao","Budhanwala","Burewal","Chachowal","Chak Bahmanian","Chak Bundala","Chak Chela","Chak Gadaipur","Chak Hathiana","Chak Rame","Chak Yusafpur Allewal","Chawinda","Danewal","Darapur","Dhadha Daulatpur","Dhandowal","Dharmiwal","Fakhruwal","Fatehpur","Fatehpur Bhagwan","Fazalwal","Gadaipur","Gatta Mundi Kasu","Gatti Pir Bakhsh","Gatti Raipur","Gehlan","Ghuduwal","Gidarpindi","Haveli","Hazipur","Heran","Ida","Indowal","Isewal","Jafarwal","Jaffarpur","Jakopur Kalan","Jakopur Khurd","Jalalpur Khurd","Jalanpur Kalan","Jamsher","Janian","Janian","Janian Chahal","Kakar Kalan","Kakar Kalan","Kakar Khurd","Kamalpur","Kang Kalan","Kang Khurd","Kanian Kalan","Kanian Khurd","Kara Ramsingh","Kasupur","Khanpur Rajputan","Khosa","Khurampur","Killi","Kohar Kalan","Kohar Khurd","Kotha","Kotla Heran","Kotla Surajmal","Kotli Gazran","Kotli Kamboan","Kular","Kutbiwal","Laksian","Langewal","Lasuri","Maharajwala","Mahmonwal","Makhi","Mala","Malliwal","Malsian","Malupur","Manak","Manakpur","Mandala","Mandi Kalu","Meda","Mehmadpur","Mehmuwal Yusafpur","Miani","Mianwal Araian","Mirpur Saidan","Mirzapur","Mohriwal","Motipur","Mubarakpur","Mulewal Araian","Mulewal Brahmana","Mulewal Khaira","Mundi Chohlian","Mundi Kasu","Mundi Shehrian","Muridwal","Nahl","Namazipur","Nangal Ambian","Nasirpur","Naurangpur","Naurangpur","Nawan Qila","Nawanpind Akaliwala","Nawanpind Donawala","Nawanpind Khalewal","Nihaluwal","Pandher","Parana","Parjian Kalan","Parjian Khurd","Pato Kalan","Pato Khurd","Phul","Pipli","Punian","Raewal Dona","Raipur","Rame","Rame Taharpur","Rampur","Raunt","Rayewal Bet","Reru","Rupewali","Sabuwal","Sadarpur","Sadiqpur","Sahlapur","Saidpur Jhiri","Sajanwal","Salah Nagar","Salaich","Saleman","Samailpur","Sand","Sandhanwal","Sangatpur","Sarangwal","Shekhewal","Shergarh","Sichewali","Sidhupur","Sindhar","Sohal","Sohal Jagir","Taharpur","Talwandi Butian","Talwandi Madho","Talwandi Sanghra","Talwara","Thamunwal","Theh Kushalgarh","Turna","Tut Shersingh","Yusafpur Allewal","Yusafpur Darewal"]}]}